./.gitignore
./.python-version
./LOCAL_INSTALLATION.pdf
./PKG-INFO
./PUBLISHING.md
./PUBLISHING.pdf
./README.md
./README.pdf
./aws_cost_and_resources_report.md
./aws_cost_and_resources_report.pdf
./build_and_publish.sh
./docker-compose.yml
./install.sh
./main.py
./pyproject.toml
./uv.lock
./.roo/system-prompt-code
./config/__init__.py
./config/settings.py
./core/__init__.py
./core/exceptions.py
./docs/aws_tools.md
./docs/aws_tools.pdf
./docs/loki_tools.md
./docs/loki_tools.pdf
./docs/mongodb_tools.md
./docs/mongodb_tools.pdf
./docs/postgresql_tools.md
./docs/postgresql_tools.pdf
./docs/prometheus_tools.md
./docs/prometheus_tools.pdf
./docs/redis_tools.md
./docs/redis_tools.pdf
./docs/vault_tools.md
./docs/vault_tools.pdf
./examples/servers/.gitattributes
./examples/servers/.gitignore
./examples/servers/.npmrc
./examples/servers/CODE_OF_CONDUCT.md
./examples/servers/CONTRIBUTING.md
./examples/servers/LICENSE
./examples/servers/README.md
./examples/servers/SECURITY.md
./examples/servers/package-lock.json
./examples/servers/package.json
./examples/servers/tsconfig.json
./examples/servers/.github/pull_request_template.md
./examples/servers/.github/workflows/python.yml
./examples/servers/.github/workflows/release.yml
./examples/servers/.github/workflows/typescript.yml
./examples/servers/.github/workflows/version-check.yml
./examples/servers/scripts/release.py
./examples/servers/src/aws-kb-retrieval-server/Dockerfile
./examples/servers/src/aws-kb-retrieval-server/README.md
./examples/servers/src/aws-kb-retrieval-server/index.ts
./examples/servers/src/aws-kb-retrieval-server/package.json
./examples/servers/src/aws-kb-retrieval-server/tsconfig.json
./examples/servers/src/brave-search/Dockerfile
./examples/servers/src/brave-search/README.md
./examples/servers/src/brave-search/index.ts
./examples/servers/src/brave-search/package.json
./examples/servers/src/brave-search/tsconfig.json
./examples/servers/src/everart/Dockerfile
./examples/servers/src/everart/README.md
msrashed100_devops_mcp-1.0.3.dist-info/METADATA
msrashed100_devops_mcp-1.0.3.dist-info/WHEEL
msrashed100_devops_mcp-1.0.3.dist-info/entry_points.txt
msrashed100_devops_mcp-1.0.3.dist-info/RECORD
