Metadata-Version: 2.4
Name: msrashed100-devops-mcp
Version: 1.0.3
Summary: A Model Context Protocol (MCP) server that provides DevOps tools and resources for Kubernetes, AWS, Prometheus, and more
Project-URL: Homepage, https://github.com/yourusername/devops-mcp-server
Project-URL: Bug Tracker, https://github.com/yourusername/devops-mcp-server/issues
Author: DevOps MCP Team
License: MIT
Keywords: aws,devops,github,kubernetes,mcp,mongodb,postgresql,prometheus,redis,vault
Classifier: Development Status :: 4 - Beta
Classifier: Intended Audience :: Developers
Classifier: License :: OSI Approved :: MIT License
Classifier: Programming Language :: Python :: 3
Classifier: Programming Language :: Python :: 3.12
Classifier: Topic :: Software Development :: Libraries :: Python Modules
Requires-Python: >=3.12
Requires-Dist: boto3>=1.34.0
Requires-Dist: httpx>=0.28.1
Requires-Dist: hvac>=1.2.1
Requires-Dist: kubernetes>=29.0.0
Requires-Dist: mcp[cli]>=1.6.0
Requires-Dist: psycopg2-binary>=2.9.9
Requires-Dist: pygithub>=2.1.1
Requires-Dist: pymongo>=4.6.1
Requires-Dist: redis>=5.0.1
